LICENSE
MANIFEST.in
README.md
compareconfig.py
pyproject.toml
setup.cfg
setup.py
conf/archive.regex.dist
conf/fuglu.conf.dist
conf/fuglu_mrtg.cfg.dist
conf/logging.conf.dist
conf/skipplugins.regex.dist
conf/rules/default-archivefiletypes.conf.dist
conf/rules/default-archivenames.conf.dist
conf/rules/default-filenames.conf.dist
conf/rules/default-filetypes.conf.dist
conf/templates/blockedfile.tmpl.dist
doc/CHANGELOG
doc/INSTALL
scripts/buildscripts/README.md
scripts/buildscripts/build-deb.sh
scripts/mrtg/fuglu_mrtg.sh
scripts/startscripts/arch/fuglu.service
scripts/startscripts/centos_rhel/6/fuglu
scripts/startscripts/centos_rhel/7/fuglu.service
scripts/startscripts/debian/7/fuglu
scripts/startscripts/debian/8/fuglu.service
scripts/startscripts/suse/13/fuglu
src/fuglu/__init__.py
src/fuglu/__main__.py
src/fuglu/addrcheck.py
src/fuglu/asyncprocpool.py
src/fuglu/bounce.py
src/fuglu/caching.py
src/fuglu/core.py
src/fuglu/daemon.py
src/fuglu/debug.py
src/fuglu/funkyconsole.py
src/fuglu/loghandlers.py
src/fuglu/logtools.py
src/fuglu/mailattach.py
src/fuglu/mixins.py
src/fuglu/mshared.py
src/fuglu/procpool.py
src/fuglu/protocolbase.py
src/fuglu/scansession.py
src/fuglu/shared.py
src/fuglu/stats.py
src/fuglu/stringencode.py
src/fuglu/threadpool.py
src/fuglu.egg-info/PKG-INFO
src/fuglu.egg-info/SOURCES.txt
src/fuglu.egg-info/dependency_links.txt
src/fuglu.egg-info/requires.txt
src/fuglu.egg-info/top_level.txt
src/fuglu/connectors/__init__.py
src/fuglu/connectors/asyncmilterconnector.py
src/fuglu/connectors/check.py
src/fuglu/connectors/esmtpconnector.py
src/fuglu/connectors/milterconnector.py
src/fuglu/connectors/ncconnector.py
src/fuglu/connectors/smtpconnector.py
src/fuglu/extensions/__init__.py
src/fuglu/extensions/aiodnsquery.py
src/fuglu/extensions/aioredisext.py
src/fuglu/extensions/dnsquery.py
src/fuglu/extensions/elastic.py
src/fuglu/extensions/filearchives.py
src/fuglu/extensions/filetype.py
src/fuglu/extensions/fuzzyhashlib.py
src/fuglu/extensions/redisext.py
src/fuglu/extensions/sql.py
src/fuglu/lib/__init__.py
src/fuglu/lib/patcheddkimlib.py
src/fuglu/lib/patchedlibmilter.py
src/fuglu/lib/ppymilterbase.py
