Metadata-Version: 2.1
Name: fuglu
Version: 1.6.0
Summary: FuGlu Mail Content Scanner
Home-page: http://www.fuglu.org
Download-URL: https://gitlab.com/fumail/fuglu/-/archive/master/fuglu-master.tar.gz
Author: O. Schacher
Author-email: oli@fuglu.org
License: Apache Software License
Classifier: Development Status :: 5 - Production/Stable
Classifier: Environment :: No Input/Output (Daemon)
Classifier: Intended Audience :: Developers
Classifier: Intended Audience :: System Administrators
Classifier: License :: OSI Approved :: Apache Software License
Classifier: Operating System :: POSIX
Classifier: Programming Language :: Python
Classifier: Topic :: Communications :: Email
Classifier: Topic :: Communications :: Email :: Filters
Classifier: Topic :: Communications :: Email :: Mail Transport Agents
Requires: domainmagic
Requires-Python: >=3.6
Provides-Extra: test
License-File: LICENSE
